tensorx/__init__.py
tensorx/__version__.py
tensorx/activation.py
tensorx/init.py
tensorx/layers.py
tensorx/logic.py
tensorx/loss.py
tensorx/math.py
tensorx/metrics.py
tensorx/ops.py
tensorx/random.py
tensorx/train/__init__.py
tensorx/train/callbacks.py
tensorx/train/model.py
tensorx/utils.py
tensorx-2.1.0.dist-info/WHEEL
tensorx-2.1.0.dist-info/METADATA
tensorx-2.1.0.dist-info/RECORD
