Metadata-Version: 2.1
Name: tensorx
Version: 2.1.0
Summary: TensorX is an open source library to build deep neural network models
Home-page: https://tensorx.org
License: Apache-2.0
Keywords: tensorx,tensorflow,tensor,machine learning,neural networks,artificial/intelligence
Author: Davide Nunes
Author-email: davidenunes@pm.me
Requires-Python: >=3.7,<3.9
Classifier: Intended Audience :: Developers
Classifier: Intended Audience :: Education
Classifier: Intended Audience :: Science/Research
Classifier: License :: OSI Approved :: Apache Software License
Classifier: Programming Language :: Python
Classifier: Programming Language :: Python :: 3
Classifier: Programming Language :: Python :: 3.7
Classifier: Programming Language :: Python :: 3.8
Classifier: Topic :: Scientific/Engineering
Classifier: Topic :: Scientific/Engineering :: Artificial Intelligence
Classifier: Topic :: Scientific/Engineering :: Mathematics
Classifier: Topic :: Software Development :: Libraries
Classifier: Topic :: Software Development :: Libraries :: Python Modules
Provides-Extra: matplotlib
Provides-Extra: pygraphviz
Provides-Extra: pyqtgraph
Provides-Extra: tensornetwork
Provides-Extra: tqdm
Requires-Dist: PyQt5 (>=5.15.0,<6.0.0); extra == "pyqtgraph"
Requires-Dist: matplotlib (>=3.3.0,<4.0.0); extra == "matplotlib"
Requires-Dist: numpy
Requires-Dist: pygraphviz; extra == "pygraphviz"
Requires-Dist: pyqtgraph (>=0.11.0,<0.12.0); extra == "pyqtgraph"
Requires-Dist: tensornetwork (>=0.4.1,<0.5.0); extra == "tensornetwork"
Requires-Dist: tqdm (>=4.48.1,<5.0.0); extra == "tqdm"
Project-URL: Repository, https://github.com/davidenunes/tensorx
